{
  "id": "I123",
  "name": "Michael Fraser A'Court",
  "givenName": "Michael Fraser",
  "surname": "A'Court",
  "sex": "M",
  "birthDate": "13 AUG 1946",
  "birthPlace": null,
  "deathDate": null,
  "deathPlace": null,
  "photos": [
    "Data/Picture/Michael A'Court.jpg"
  ],
  "spouseIds": [
    "I129"
  ],
  "childIds": [
    "I130"
  ],
  "parentIds": [
    "I119",
    "I121"
  ],
  "marriages": [
    {
      "spouseId": "I129",
      "familyId": "F87"
    }
  ],
  "avatar": "avatars/I123_0.jpg"
}