{
  "id": "I1459",
  "name": "James A'Court",
  "givenName": "James",
  "surname": "A'Court",
  "sex": "M",
  "birthDate": "ABT 1853",
  "birthPlace": "Marnhull, Dorset",
  "deathDate": null,
  "deathPlace": null,
  "photos": [
    "Data/Media/1911 census/London/Ealing/RG14 6895 79.jpg"
  ],
  "spouseIds": [
    "I1460"
  ],
  "childIds": [
    "I1456",
    "I1462",
    "I1463"
  ],
  "parentIds": [],
  "occupations": [
    "Dray Man",
    "Labourer",
    "Labourer",
    "General labourer",
    "Park Gardener"
  ],
  "notes": [
    "Roy, I expect you spotted this on the Dorset list:-"
  ],
  "censusRecords": [
    {
      "date": "1881",
      "place": "Marnhull, Dorset, Burges"
    },
    {
      "date": "1891",
      "place": "Marnhull, Dorset, Zinc Cottages Nr. Walton Elm Malthouse"
    },
    {
      "date": "1901",
      "place": "Middlesex, Ealing,13 Norfolk Terrace, Northfield Lane."
    },
    {
      "date": "1911",
      "place": "Ealing, Middlesex, 55 Northfield Avenue"
    }
  ],
  "marriages": [
    {
      "spouseId": "I1460",
      "familyId": "F561"
    }
  ],
  "avatar": "avatars/I1459_0.jpg"
}