{
  "id": "I1602",
  "name": "Henry J A'Court",
  "givenName": "Henry J",
  "surname": "A'Court",
  "sex": "M",
  "birthDate": "Abt 1863",
  "birthPlace": "Bristol, Bedminster",
  "deathDate": null,
  "deathPlace": null,
  "photos": [
    "Data/Media/1881 census/Lancs/Warrington/RG11 3797 52 12.jpg"
  ],
  "spouseIds": [
    "I1603"
  ],
  "childIds": [
    "I1604",
    "I1616",
    "I1605",
    "I1606",
    "I1607",
    "I1608",
    "I2613"
  ],
  "parentIds": [
    "I1765",
    "I2258"
  ],
  "occupations": [
    "Wire Labourer",
    "Labourer plate worker",
    "Railway Signal Fitter",
    "Chargeman Signals LNW Railway"
  ],
  "censusRecords": [
    {
      "date": "1881",
      "place": "Lancashire, Warrington, 34 Chorley St."
    },
    {
      "date": "1891",
      "place": "Lancashire, Wavertree, 13 Upper cross St."
    },
    {
      "date": "1901",
      "place": "St. Helens, Lancs, 10 South John St"
    },
    {
      "date": "1911",
      "place": "St. Helens, Lancs, 9 South John St"
    }
  ],
  "marriages": [
    {
      "spouseId": "I1603",
      "familyId": "F693",
      "marriageDate": "ABT 1883"
    }
  ],
  "avatar": "avatars/I1602_0.jpg"
}