{
  "id": "I2219",
  "name": "William Pilot",
  "givenName": "William",
  "surname": "Pilot",
  "sex": "M",
  "birthDate": "ABT 1795",
  "birthPlace": "England",
  "deathDate": null,
  "deathPlace": null,
  "photos": [],
  "spouseIds": [
    "I2220"
  ],
  "childIds": [
    "I2187"
  ],
  "parentIds": [],
  "occupations": [
    "Blacksmith"
  ],
  "marriages": [
    {
      "spouseId": "I2220",
      "familyId": "F786",
      "marriageDate": "28 SEP 1818",
      "marriagePlace": "Wetbury-On-Trym, Bristol"
    }
  ]
}