{
  "id": "I2989",
  "name": "Marie Gertrude Unknown",
  "givenName": "Marie Gertrude",
  "surname": "Unknown",
  "sex": "F",
  "birthDate": "1894",
  "birthPlace": "London, Highbury",
  "deathDate": null,
  "deathPlace": null,
  "photos": [],
  "spouseIds": [
    "I2733"
  ],
  "childIds": [
    "I2990"
  ],
  "parentIds": [],
  "censusRecords": [
    {
      "date": "1921",
      "place": "London, East Finchley, 49 Bedford Rd."
    }
  ],
  "marriages": [
    {
      "spouseId": "I2733",
      "familyId": "F1029"
    }
  ]
}